<?xml version="1.0" encoding="UTF-8"?>
<Information>
	<GraphType>EightNeighborSquareGraph</GraphType>
	<EdgeType>Toroidal</EdgeType>
	<Model>GameOfLife</Model>
	<Author>Sierra</Author>
	<Title>Brown Fire</Title>
	<GridRows>100</GridRows>
	<GridColumns>100</GridColumns>
	<Configuration>
		<Cell x="51" y="50" state="alive"> </Cell>
		<Cell x="50" y="51" state="alive"> </Cell>
		<Cell x="52" y="50" state="alive"> </Cell>
		<Cell x="51" y="51" state="alive"> </Cell>
		<Cell x="51" y="52" state="alive"> </Cell>
	</Configuration>
</Information>