<?xml version="1.0" encoding="UTF-8"?>
<Information>
	<Model>GameOfLife</Model>
	<Author>Sierra</Author>
	<Title>Brown Fire</Title>
	<GridRows>20</GridRows>
	<GridColumns>20</GridColumns>
	<Parameters>
		<probCatch>0.15</probCatch>
	</Parameters>
	<Configuration>
		<Cell x="3" y="3" state="alive"> </Cell>
		<Cell x="4" y="4" state="alive"> </Cell>
		<Cell x="5" y="4" state="alive"> </Cell>
		<Cell x="5" y="3" state="alive"> </Cell>
		<Cell x="4" y="5" state="alive"> </Cell>
	</Configuration>
</Information>